<?xml version="1.0" encoding="UTF-8"?>
<MetaDataObject xmlns="http://v8.1c.ru/8.3/MDClasses" xmlns:app="http://v8.1c.ru/8.2/managed-application/core" xmlns:cfg="http://v8.1c.ru/8.1/data/enterprise/current-config" xmlns:cmi="http://v8.1c.ru/8.2/managed-application/cmi" xmlns:ent="http://v8.1c.ru/8.1/data/enterprise" xmlns:lf="http://v8.1c.ru/8.2/managed-application/logform" xmlns:style="http://v8.1c.ru/8.1/data/ui/style" xmlns:sys="http://v8.1c.ru/8.1/data/ui/fonts/system" xmlns:v8="http://v8.1c.ru/8.1/data/core" xmlns:v8ui="http://v8.1c.ru/8.1/data/ui" xmlns:web="http://v8.1c.ru/8.1/data/ui/colors/web" xmlns:win="http://v8.1c.ru/8.1/data/ui/colors/windows" xmlns:xen="http://v8.1c.ru/8.3/xcf/enums" xmlns:xpr="http://v8.1c.ru/8.3/xcf/predef" xmlns:xr="http://v8.1c.ru/8.3/xcf/readable" xmlns:xs="http://www.w3.org/2001/XMLSchema" xmlns:xsi="http://www.w3.org/2001/XMLSchema-instance">
	<Catalog uuid="11898ce0-0ca2-4f3b-b01b-07f0e529543b">
		<InternalInfo>
			<xr:GeneratedType name="CatalogObject.МаркетинговыеАкции" category="Object">
				<xr:TypeId>6e09bce8-cdea-439d-a17a-49521711e2d6</xr:TypeId>
				<xr:ValueId>fd37e8fa-8089-4bf8-a5c8-0b69c329610c</xr:ValueId>
			</xr:GeneratedType>
			<xr:GeneratedType name="CatalogRef.МаркетинговыеАкции" category="Ref">
				<xr:TypeId>f1c7f072-110d-46c5-84a3-d6ee0cdd9dfa</xr:TypeId>
				<xr:ValueId>addb27cb-0d8d-4768-b5a4-47d419530f94</xr:ValueId>
			</xr:GeneratedType>
			<xr:GeneratedType name="CatalogSelection.МаркетинговыеАкции" category="Selection">
				<xr:TypeId>0a88352b-ac68-4106-b803-44f41cc62b7a</xr:TypeId>
				<xr:ValueId>4d07eb71-30c3-404d-b279-88b5e92e5c85</xr:ValueId>
			</xr:GeneratedType>
			<xr:GeneratedType name="CatalogList.МаркетинговыеАкции" category="List">
				<xr:TypeId>d0c19627-4cb7-45be-8b88-1b00c361aa7a</xr:TypeId>
				<xr:ValueId>528bdbf4-9bf9-4180-9068-118915675485</xr:ValueId>
			</xr:GeneratedType>
			<xr:GeneratedType name="CatalogManager.МаркетинговыеАкции" category="Manager">
				<xr:TypeId>f9698d11-129c-4dce-afb6-f4800bf2a0f5</xr:TypeId>
				<xr:ValueId>21e31d25-7225-45bf-b455-be66ae84f1b4</xr:ValueId>
			</xr:GeneratedType>
		</InternalInfo>
		<Properties>
			<Name>МаркетинговыеАкции</Name>
			<Synonym>
				<v8:item>
					<v8:lang>ru</v8:lang>
					<v8:content>Маркетинговые акции</v8:content>
				</v8:item>
			</Synonym>
			<Comment/>
			<Hierarchical>false</Hierarchical>
			<HierarchyType>HierarchyFoldersAndItems</HierarchyType>
			<LimitLevelCount>false</LimitLevelCount>
			<LevelCount>2</LevelCount>
			<FoldersOnTop>true</FoldersOnTop>
			<UseStandardCommands>true</UseStandardCommands>
			<Owners/>
			<SubordinationUse>ToItems</SubordinationUse>
			<CodeLength>9</CodeLength>
			<DescriptionLength>25</DescriptionLength>
			<CodeType>String</CodeType>
			<CodeAllowedLength>Variable</CodeAllowedLength>
			<CodeSeries>WholeCatalog</CodeSeries>
			<CheckUnique>true</CheckUnique>
			<Autonumbering>true</Autonumbering>
			<DefaultPresentation>AsDescription</DefaultPresentation>
			<Characteristics/>
			<PredefinedDataUpdate>Auto</PredefinedDataUpdate>
			<EditType>InDialog</EditType>
			<QuickChoice>false</QuickChoice>
			<ChoiceMode>BothWays</ChoiceMode>
			<InputByString>
				<xr:Field>Catalog.МаркетинговыеАкции.StandardAttribute.Description</xr:Field>
				<xr:Field>Catalog.МаркетинговыеАкции.StandardAttribute.Code</xr:Field>
			</InputByString>
			<SearchStringModeOnInputByString>Begin</SearchStringModeOnInputByString>
			<FullTextSearchOnInputByString>DontUse</FullTextSearchOnInputByString>
			<ChoiceDataGetModeOnInputByString>Directly</ChoiceDataGetModeOnInputByString>
			<DefaultObjectForm/>
			<DefaultFolderForm/>
			<DefaultListForm/>
			<DefaultChoiceForm/>
			<DefaultFolderChoiceForm/>
			<AuxiliaryObjectForm/>
			<AuxiliaryFolderForm/>
			<AuxiliaryListForm/>
			<AuxiliaryChoiceForm/>
			<AuxiliaryFolderChoiceForm/>
			<IncludeHelpInContents>false</IncludeHelpInContents>
			<BasedOn/>
			<DataLockFields/>
			<DataLockControlMode>Automatic</DataLockControlMode>
			<FullTextSearch>Use</FullTextSearch>
			<ObjectPresentation/>
			<ExtendedObjectPresentation/>
			<ListPresentation/>
			<ExtendedListPresentation/>
			<Explanation/>
			<CreateOnInput>Use</CreateOnInput>
			<ChoiceHistoryOnInput>Auto</ChoiceHistoryOnInput>
		</Properties>
		<ChildObjects/>
	</Catalog>
</MetaDataObject>